oblig2/fulladder.vhd
library IEEE;
use IEEE.STD_LOGIC_1164.all;

entity fulladder is 
 port(a, b, cin: in  STD_LOGIC;
      cout, s:   out STD_LOGIC);
end ;

architecture synth of fulladder is 
begin
 cout <= ((a xor b) and cin) or (a and b);
 s <= (a xor b) xor cin;
end;

oblig2/CLA_block.vhd
library IEEE;
use IEEE.STD_LOGIC_1164.all;

entity CLA_block is
port(
 a, b : in std_logic_vector(3 downto 0);
 cin  : in std_logic;
 s    : out std_logic_vector(3 downto 0);
 cout : out std_logic);
end entity CLA_block;

architecture mixed of CLA_block is

component fulladder
 port(
    a, b, cin: in  STD_LOGIC;
      cout, s: out STD_LOGIC
 );
end component;

signal p, g:     std_logic_vector(3 downto 0);
signal c:        std_logic_vector(4 downto 0);
signal p30, g30: STD_LOGIC;

begin
  g(0) <= a(0) and b(0); g(1) <= a(1) and b(1);
  g(2) <= a(2) and b(2); g(3) <= a(3) and b(3);

  p(0) <= a(0) or b(0); p(1) <= a(1) or b(1);
  p(2) <= a(2) or b(2); p(3) <= a(3) or b(3);
 
  p30 <= and p;
  g30 <= (((((p(1) and g(0)) or g(1)) and p(2)) or g(2)) and p(3)) or g(3);

  c(0) <= cin;
  c(1) <= g(0) or (p(0) and cin);
  c(2) <= g(1) or (p(1) and c(1));
  c(3) <= g(2) or (p(2) and c(2));
  c(4) <= g(3) or (p(3) and c(3));

  cout <= ((((((p(1) and g(0)) or g(1)) and p(2)) or g(2)) and p(3)) or g(3)) or ((and p) and cin); -- = c(4)
  --cout <= c(4);

FA1: fulladder port map(a(0), b(0), c(0), c(1), s(0));
FA2: fulladder port map(a(1), b(1), c(1), c(2), s(1));
FA3: fulladder port map(a(2), b(2), c(2), c(3), s(2));
FA4: fulladder port map(a(3), b(3), c(3), c(4), s(3));
end mixed;

Oblig2/CLA_top.vhd
library IEEE;
use IEEE.STD_LOGIC_1164.all;

entity CLA_top is
generic(width : positive := 32);
port(
 a, b : in std_logic_vector(width-1 downto 0);
 cin  : in std_logic;
 sum  : out std_logic_vector(width-1 downto 0);
 cout : out std_logic);
end entity CLA_top;

architecture struct of CLA_top is
component CLA_block
port(
 a, b : in std_logic_vector(3 downto 0);
 cin  : in std_logic;
 s    : out std_logic_vector(3 downto 0);
 cout : out std_logic);
end component;

signal c : std_logic_vector(width/4 - 1 downto 0);
begin

CLA1 : CLA_block port map(a => a(3 downto 0), b => b(3 downto 0), cin => cin, s => sum(3 downto 0), cout => c(0));
CLA2 : CLA_block port map(a => a(7 downto 4), b => b(7 downto 4), cin => c(0), s => sum(7 downto 4), cout => c(1));
CLA3 : CLA_block port map(a => a(11 downto 8), b => b(11 downto 8), cin => c(1), s => sum(11 downto 8), cout => c(2));
CLA4 : CLA_block port map(a => a(15 downto 12), b => b(15 downto 12), cin => c(2), s => sum(15 downto 12), cout => c(3));
CLA5 : CLA_block port map(a => a(19 downto 16), b => b(19 downto 16), cin => c(3), s => sum(19 downto 16), cout => c(4));
CLA6 : CLA_block port map(a => a(23 downto 20), b => b(23 downto 20), cin => c(4), s => sum(23 downto 20), cout => c(5));
CLA7 : CLA_block port map(a => a(27 downto 24), b => b(27 downto 24), cin => c(5), s => sum(27 downto 24), cout => c(6));
CLA8 : CLA_block port map(a => a(31 downto 28), b => b(31 downto 28), cin => c(6), s => sum(31 downto 28), cout => c(7));

cout <= c(width/4 - 1);
end;

oblig2/tb_CLA_top.vhd
library IEEE;
use IEEE.STD_LOGIC_1164.all;
use IEEE.numeric_std.all;

entity tb_CLA_top is
end entity tb_CLA_top;

architecture behavioral of tb_CLA_top is

component CLA_top is
generic(width : positive := 32);
port(
 a, b : in std_logic_vector(width-1 downto 0);
 cin  : in std_logic;
 sum  : out std_logic_vector(width-1 downto 0);
 cout : out std_logic);
end component;

-- Tilordning av startverdi ved deklarasjon gjøres med :=
signal tb_a, tb_b : std_logic_vector(31 downto 0) := (others => '0');
signal tb_cin     : std_logic := '0';

-- outputs bør ikke få en startverdi i testbenken, da det kan maskere feil.
signal tb_s    : std_logic_vector(31 downto 0);
signal tb_cout : std_logic;

begin
-- instansiering:
DUT: CLA_top -- Merkelappen DUT betyr «device under test» som er en av mange
port map( -- vanlige betegnelser på simuleringsobjektet.
	a => tb_a, -- Mappinger gjøres med =>, til forskjell fra tilordninger som
	b => tb_b, -- bruker <= eller :=
	cin => tb_cin, -- Mappinger kan ses på en ren sammenkobling av ledninger
	sum => tb_s, -- Vi mapper alltid testenhetens porter til testbenkens signaler
	cout => tb_cout -- Siste informasjon før parantes-slutt har ikke ',' eller ';'
);
-- I testbenker kan vi ha prosesser uten sensitivitetsliste..
-- i slike prosesser kan vi angi tid med «wait» statements, og
-- vi kan sette signaler flere ganger etter hverandre uten å gi konflikter.
-- NB: Prosessen vil trigges om og om igjen om vi ikke hindrer det.
process
begin
	wait for 10 ns;
	-- Test 0
	tb_a <= std_logic_vector(to_unsigned(1,32)); 
	tb_b <= std_logic_vector(to_unsigned(2,32)); tb_cin <= '0'; wait for 10 ns;
  	assert (tb_s = std_logic_vector(to_unsigned(3,32)) and tb_cout = '0') 
	report "Failure, test 0 : Expected sum = " & to_string(to_unsigned(3,32)) & ", got " & to_string(unsigned(tb_s)) 
		& ". Expected cout = '0', got " & to_string(tb_cout) severity failure;

	-- Test 1
	tb_a <= std_logic_vector(to_unsigned(5,32)); 
	tb_b <= std_logic_vector(to_unsigned(6,32)); tb_cin <= '1'; wait for 10 ns;
	assert (tb_s = std_logic_vector(to_unsigned(12,32)) and tb_cout = '0') 
	report "Failure, test 1 : Expected sum = " & to_string(to_unsigned(12,32)) & ", got " & to_string(unsigned(tb_s)) 
		& ". Expected cout = '0', got " & to_string(tb_cout) severity failure;

	-- Test 2 
	tb_a <= std_logic_vector(to_unsigned(2000000000,32)); 
	tb_b <= std_logic_vector(to_unsigned(100000000,32)); tb_cin <= '0'; wait for 10 ns;
	assert (tb_s = std_logic_vector(to_unsigned(2100000000,32)) and tb_cout = '0') 
	report "Failure, test 2 : Expected sum = " & to_string(to_unsigned(2100000000,32)) & ", got " & to_string(unsigned(tb_s)) 
		& ". Expected cout = '0', got " & to_string(tb_cout) severity failure;

	-- Test 3 )
	tb_a <= std_logic_vector(to_unsigned(111,32)); 
	tb_b <= std_logic_vector(to_unsigned(222,32)); tb_cin <= '0'; wait for 10 ns;
	assert (tb_s = std_logic_vector(to_unsigned(333,32)) and tb_cout = '0') 
	report "Failure, test 3 : Expected sum = " & to_string(to_unsigned(333,32)) & ", got " & to_string(unsigned(tb_s)) 
		& ". Expected cout = '0', got " & std_logic'image(tb_cout) severity failure;

	-- Test 4
	tb_a <= std_logic_vector(to_unsigned(555,32)); 
	tb_b <= std_logic_vector(to_unsigned(444,32)); tb_cin <= '0'; wait for 10 ns;
	assert (tb_s = std_logic_vector(to_unsigned(999,32)) and tb_cout = '0') 
	report "Failure, test 4 : Expected sum = " & to_string(to_unsigned(999,32)) & ", got " & to_string(unsigned(tb_s)) 
		& ". Expected cout = '0', got " & to_string(tb_cout) severity failure;

	-- Test 5
	tb_a <= std_logic_vector(to_unsigned(15,32)); 
	tb_b <= std_logic_vector(to_unsigned(25,32)); tb_cin <= '1'; wait for 10 ns;
	assert (tb_s = std_logic_vector(to_unsigned(41,32)) and tb_cout = '0') 
	report "Failure, test 5 : Expected sum = " & to_string(to_unsigned(3,32)) & ", got " & to_string(unsigned(tb_s)) 
		& ". Expected cout = '0', got " & to_string(tb_cout) severity failure;

	-- Test 6
	tb_a <= std_logic_vector(to_unsigned(1200,32)); 
	tb_b <= std_logic_vector(to_unsigned(800,32)); tb_cin <= '0'; wait for 10 ns;
	assert (tb_s = std_logic_vector(to_unsigned(2000,32)) and tb_cout = '0') 
	report "Failure, test 6 : Expected sum = " & to_string(to_unsigned(2000,32)) & ", got " & to_string(unsigned(tb_s)) 
		& ". Expected cout = '0', got " & to_string(tb_cout) severity failure;

	-- Test 7
	tb_a <= std_logic_vector(to_unsigned(500,32)); 
	tb_b <= std_logic_vector(to_unsigned(1500,32)); tb_cin <= '1'; wait for 10 ns;
	assert (tb_s = std_logic_vector(to_unsigned(2001,32)) and tb_cout = '0') 
	report "Failure, test 7 : Expected sum = " & to_string(to_unsigned(2001,32)) & ", got " & to_string(unsigned(tb_s)) 
		& ". Expected cout = '0', got " & to_string(tb_cout) severity failure;

	-- Test 8
	tb_a <= std_logic_vector(to_unsigned(1300,32)); 
	tb_b <= std_logic_vector(to_unsigned(700,32)); tb_cin <= '0'; wait for 10 ns;
	assert (tb_s = std_logic_vector(to_unsigned(2000,32)) and tb_cout = '0') 
	report "Failure, test 8 : Expected sum = " & to_string(to_unsigned(2000,32)) & ", got " & to_string(unsigned(tb_s)) 
		& ". Expected cout = '0', got " & to_string(tb_cout) severity failure;

	-- Test MSB 
	tb_a <= std_logic_vector(to_unsigned(2147483647,32));
	tb_b <= std_logic_vector(to_signed(-2147483647,32));  
	tb_cin <= '0';
	wait for 10 ns;
	assert (tb_s = std_logic_vector(to_unsigned(0,32)) and tb_cout = '1')
	report "Failure, MSB Only Test : Expected sum = " & to_string(to_unsigned(0,32)) & ", got " & to_string(unsigned(tb_s))
	& ". Expected cout = '1', got " & to_string(tb_cout) severity failure;

	-- Test Overflow 
	tb_a <= "11111111111111111111111111111111";  -- 4294967295 in binary
	tb_b <= std_logic_vector(to_unsigned(1,32));
	tb_cin <= '0';
	wait for 10 ns;
	assert (tb_s = "00000000000000000000000000000000" and tb_cout = '1')
	report "Failure, Overflow Test : Expected sum = " & to_string(to_unsigned(0,32)) & ", got " & to_string(unsigned(tb_s))
	& ". Expected cout = '1', got " & to_string(tb_cout) severity failure;

	-- Test Overflow igjen
	tb_a <= std_logic_vector(to_signed(15,32)); 
	tb_b <= std_logic_vector(to_signed(-15,32));
	tb_cin <= '0';
	wait for 10 ns;
	assert (tb_s = std_logic_vector(to_signed(0,32)) and tb_cout = '1')
	report "Failure, General Test with MSB : Expected sum = " & to_string(to_unsigned(0,32)) & ", got " & to_string(unsigned(tb_s))
	& ". Expected cout = '1', got " & to_string(tb_cout) severity failure;

	report("CLA_top - Alt stemmer!") severity note;
	std.env.stop; -- stopper simuleringen
	end process;
end architecture behavioral;

oblig2/cla_top.vcd
$date
	Tue Sep 26 13:42:23 2023
$end
$version
	QuestaSim Version 2020.4
$end
$timescale
	1ns
$end
$scope module tb_cla_top $end
$scope module DUT $end
$var wire 1 ! a [31] $end
$var wire 1 " a [30] $end
$var wire 1 # a [29] $end
$var wire 1 $ a [28] $end
$var wire 1 % a [27] $end
$var wire 1 & a [26] $end
$var wire 1 ' a [25] $end
$var wire 1 ( a [24] $end
$var wire 1 ) a [23] $end
$var wire 1 * a [22] $end
$var wire 1 + a [21] $end
$var wire 1 , a [20] $end
$var wire 1 - a [19] $end
$var wire 1 . a [18] $end
$var wire 1 / a [17] $end
$var wire 1 0 a [16] $end
$var wire 1 1 a [15] $end
$var wire 1 2 a [14] $end
$var wire 1 3 a [13] $end
$var wire 1 4 a [12] $end
$var wire 1 5 a [11] $end
$var wire 1 6 a [10] $end
$var wire 1 7 a [9] $end
$var wire 1 8 a [8] $end
$var wire 1 9 a [7] $end
$var wire 1 : a [6] $end
$var wire 1 ; a [5] $end
$var wire 1 < a [4] $end
$var wire 1 = a [3] $end
$var wire 1 > a [2] $end
$var wire 1 ? a [1] $end
$var wire 1 @ a [0] $end
$var wire 1 A b [31] $end
$var wire 1 B b [30] $end
$var wire 1 C b [29] $end
$var wire 1 D b [28] $end
$var wire 1 E b [27] $end
$var wire 1 F b [26] $end
$var wire 1 G b [25] $end
$var wire 1 H b [24] $end
$var wire 1 I b [23] $end
$var wire 1 J b [22] $end
$var wire 1 K b [21] $end
$var wire 1 L b [20] $end
$var wire 1 M b [19] $end
$var wire 1 N b [18] $end
$var wire 1 O b [17] $end
$var wire 1 P b [16] $end
$var wire 1 Q b [15] $end
$var wire 1 R b [14] $end
$var wire 1 S b [13] $end
$var wire 1 T b [12] $end
$var wire 1 U b [11] $end
$var wire 1 V b [10] $end
$var wire 1 W b [9] $end
$var wire 1 X b [8] $end
$var wire 1 Y b [7] $end
$var wire 1 Z b [6] $end
$var wire 1 [ b [5] $end
$var wire 1 \ b [4] $end
$var wire 1 ] b [3] $end
$var wire 1 ^ b [2] $end
$var wire 1 _ b [1] $end
$var wire 1 ` b [0] $end
$var wire 1 a cin $end
$var wire 1 b sum [31] $end
$var wire 1 c sum [30] $end
$var wire 1 d sum [29] $end
$var wire 1 e sum [28] $end
$var wire 1 f sum [27] $end
$var wire 1 g sum [26] $end
$var wire 1 h sum [25] $end
$var wire 1 i sum [24] $end
$var wire 1 j sum [23] $end
$var wire 1 k sum [22] $end
$var wire 1 l sum [21] $end
$var wire 1 m sum [20] $end
$var wire 1 n sum [19] $end
$var wire 1 o sum [18] $end
$var wire 1 p sum [17] $end
$var wire 1 q sum [16] $end
$var wire 1 r sum [15] $end
$var wire 1 s sum [14] $end
$var wire 1 t sum [13] $end
$var wire 1 u sum [12] $end
$var wire 1 v sum [11] $end
$var wire 1 w sum [10] $end
$var wire 1 x sum [9] $end
$var wire 1 y sum [8] $end
$var wire 1 z sum [7] $end
$var wire 1 { sum [6] $end
$var wire 1 | sum [5] $end
$var wire 1 } sum [4] $end
$var wire 1 ~ sum [3] $end
$var wire 1 !! sum [2] $end
$var wire 1 "! sum [1] $end
$var wire 1 #! sum [0] $end
$var wire 1 $! cout $end
$var wire 1 %! c [7] $end
$var wire 1 &! c [6] $end
$var wire 1 '! c [5] $end
$var wire 1 (! c [4] $end
$var wire 1 )! c [3] $end
$var wire 1 *! c [2] $end
$var wire 1 +! c [1] $end
$var wire 1 ,! c [0] $end
$upscope $end
$upscope $end
$enddefinitions $end
#0
0!
0"
0#
0$
0%
0&
0'
0(
0)
0*
0+
0,
0-
0.
0/
00
01
02
03
04
05
06
07
08
09
0:
0;
0<
0=
0>
0?
0@
0A
0B
0C
0D
0E
0F
0G
0H
0I
0J
0K
0L
0M
0N
0O
0P
0Q
0R
0S
0T
0U
0V
0W
0X
0Y
0Z
0[
0\
0]
0^
0_
0`
0a
0b
0c
0d
0e
0f
0g
0h
0i
0j
0k
0l
0m
0n
0o
0p
0q
0r
0s
0t
0u
0v
0w
0x
0y
0z
0{
0|
0}
0~
0!!
0"!
0#!
0$!
0%!
0&!
0'!
0(!
0)!
0*!
0+!
0,!
0%!
0&!
0'!
0(!
0)!
0*!
0+!
0,!
0#!
0b
0c
0d
0f
0g
0h
0j
0k
0l
0n
0o
0p
0r
0s
0t
0v
0w
0x
0z
0{
0|
0~
0!!
0"!
0$!
0e
0i
0m
0q
0u
0y
0}
#10
1_
1@
1"!
1#!
#20
1a
1^
1>
0"!
0#!
1~
1!!
#30
0a
1F
1H
1I
1J
1K
1L
1N
1P
1Q
1R
1S
1X
0^
0_
1"
1#
1$
1&
1'
1(
1+
1,
1.
10
11
14
16
0>
0@
1c
1d
1e
0h
0j
0k
1s
1t
1u
1w
1y
0"!
0#!
1'!
1)!
1f
1l
1n
1p
0~
0!!
1g
1i
1q
#40
0F
0H
0I
0J
0K
0L
0N
0P
0Q
0R
0S
0X
1Y
1Z
1\
1]
1^
1_
0"
0#
0$
0&
0'
0(
0+
0,
0.
00
01
04
06
1:
1;
1=
1>
1?
1@
0c
0d
0e
0h
0j
0k
0s
0t
0u
0w
1y
0z
0|
0}
1#!
0'!
0)!
1+!
1,!
0f
0g
0l
0n
0p
1~
1!!
0i
0q
1{
#50
1X
0Z
1[
0_
17
0:
0>
1x
1y
1|
1!!
1"!
0+!
1z
0w
0~
#60
1a
0X
0Y
0[
0^
1`
07
0;
1>
0x
0y
0z
1#!
0"!
0{
0!!
1~
#70
0a
1W
1X
1[
0\
0]
0`
16
19
1;
1<
0=
0>
0?
0@
1w
1x
1y
1z
0!!
0"!
0#!
0,!
1{
0~
0|
1}
#80
1a
1V
0W
1Y
1Z
0[
1\
1]
1^
06
18
1:
1>
1x
1y
1z
0|
1}
0~
1#!
1+!
1,!
1{
#90
0a
0V
1W
0X
0Z
1[
16
09
0:
0;
1x
1y
1z
0#!
0+!
1w
0v
#100
1A
0W
0Y
0[
0\
0]
0^
1`
1"
1#
1$
1%
1&
1'
1(
1)
1*
1+
1,
1-
1.
1/
10
11
12
13
14
15
17
19
1:
1;
1=
1?
1@
0b
0c
0d
0e
0f
0g
0h
0i
0j
0k
0l
0m
0n
0o
0p
0q
0r
0s
0t
0u
0v
0{
0}
0!!
0"!
1+!
0z
0~
1*!
0x
0y
1)!
0w
1(!
1'!
1&!
1%!
1$!
#110
0A
1!
#120
1A
1B
1C
1D
1E
1F
1G
1H
1I
1J
1K
1L
1M
1N
1O
1P
1Q
1R
1S
1T
1U
1V
1W
1X
1Y
1Z
1[
1\
0!
0"
0#
0$
0%
0&
0'
0(
0)
0*
0+
0,
0-
0.
0/
00
01
02
03
04
05
06
07
08
09
0:
0;
0<
