oblig2/fulladder.vhd
library IEEE;
use IEEE.STD_LOGIC_1164.all;

entity fulladder is 
 port(a, b, cin: in  STD_LOGIC;
      cout, s:   out STD_LOGIC);
end ;

architecture synth of fulladder is 
begin
 cout <= ((a xor b) and cin) or (a and b);
 s <= (a xor b) xor cin;
end;

Oblig2/tb_fulladder.vhd
library IEEE;
use IEEE.STD_LOGIC_1164.all;

entity tb_fulladder is
end entity tb_fulladder;

architecture behavioral of tb_fulladder is
-- en komponent er en entitet definert i en annen fil, og som vi vil bruke.
-- komponentdeklarasjonen må matcheentiteten
component fulladder is 
 port(
  a, b : in   STD_LOGIC;
  cin  : in   STD_LOGIC;
  s    : out  STD_LOGIC;
  cout : out  STD_LOGIC
);
end component;

--Tilordning av startverdi ved deklarasjon gjøres med :=
signal   tb_a, tb_b, tb_cin  : std_logic := '0';

--outputs bør ikke få en startverdi i testbenen, da det kan maskere feil.
signal tb_s, tb_cout : std_logic;

begin
 --instansiering:
DUT: fulladder    -- Merkelappen DUT betyr "device under test" som er en av mange
port map(         -- vanlige betegnelser på simuleringsobjektet.
  a     => tb_a,  -- Mappinger gjøres med =>, til forskjell fra tilordninger som
  b     => tb_b,  -- bruker <= eller :=
  cin   => tb_cin,-- Mappinger kan ses på en ren sammenkobling av ledninger
  s     => tb_s,  -- Vi mapper alltid testenhetens porter til testbenkens signaler
  cout  => tb_cout-- Siste informasjon før parentes-slutt har ikke ',' eller ';'
);

-- I testbenker kan vi ha prosesser uten sensitivitetsliste..
-- i slike prosesser kan vi angi tid med "wait" statements, og
-- vi kan sette signaler flere ganger etter hverandre uten å gi konflikter
-- NB: Prosessen vil trigges om og om igjen om vi ikke hindrer det
process
begin
 report "Starting simulation";
 wait for 10 ns;
 tb_a <= '0'; tb_b <= '0'; tb_cin <= '0'; wait for 10 ns;--0
 tb_a <= '1'; tb_b <= '0'; tb_cin <= '0'; wait for 10 ns;--1 
 tb_a <= '0'; tb_b <= '1'; tb_cin <= '0'; wait for 10 ns;--2
 tb_a <= '1'; tb_b <= '1'; tb_cin <= '0'; wait for 10 ns;--3 
 tb_a <= '0'; tb_b <= '0'; tb_cin <= '1'; wait for 10 ns;--4
 tb_a <= '1'; tb_b <= '0'; tb_cin <= '1'; wait for 10 ns;--5 
 tb_a <= '0'; tb_b <= '1'; tb_cin <= '1'; wait for 10 ns;--6
 tb_a <= '1'; tb_b <= '1'; tb_cin <= '1'; wait for 10 ns;--7 
 wait for 10 ns;

 report("Ferdig") severity note;
 std.env.stop;  -- stopper simulering
end process;
end architecture behavioral;

Oblig2/fulladdertest.vcd
$date
	Fri Sep 22 18:19:08 2023
$end
$version
	QuestaSim Version 2020.4
$end
$timescale
	1ns
$end
$scope module tb_fulladder $end
$scope module DUT $end
$var wire 1 ! a $end
$var wire 1 " b $end
$var wire 1 # cin $end
$var wire 1 $ cout $end
$var wire 1 % s $end
$upscope $end
$upscope $end
$enddefinitions $end
#0
0!
0"
0#
0$
0%
0$
0%
#20
1!
1%
#30
1"
0!
#40
1!
0%
1$
#50
1#
0"
0!
1%
0$
#60
1!
0%
1$
#70
1"
0!
#80
1!
1%
